autoclass/__init__.py
autoclass/_version.py
autoclass/autoargs_.py
autoclass/autoclass_.py
autoclass/autodict_.py
autoclass/autoeq_.py
autoclass/autohash_.py
autoclass/autoprops_.py
autoclass/autorepr_.py
autoclass/autoslots_.py
autoclass/py.typed
autoclass/utils.py
autoclass-2.2.0.dist-info/LICENSE
autoclass-2.2.0.dist-info/METADATA
autoclass-2.2.0.dist-info/WHEEL
autoclass-2.2.0.dist-info/top_level.txt
autoclass-2.2.0.dist-info/RECORD
