Metadata-Version: 2.1
Name: autoclass
Version: 2.2.0
Summary: Helps you write compact python classes
Home-page: https://github.com/smarie/python-autoclass
Maintainer: Sylvain MARIE
Maintainer-email: sylvain.marie@se.com
License: BSD 3-Clause
Download-URL: https://github.com/smarie/python-autoclass/tarball/2.2.0
Keywords: auto code generator getter setter constructor autoarg autoprops decorator property properties fields attribute attr contract object class enforce valid boilerplate pep484 type-hints runtime-typechecking typechecking
Platform: UNKNOWN
Classifier: Development Status :: 5 - Production/Stable
Classifier: Intended Audience :: Developers
Classifier: Topic :: Software Development :: Libraries :: Python Modules
Classifier: License :: OSI Approved :: BSD License
Classifier: Programming Language :: Python :: 2.7
Classifier: Programming Language :: Python :: 3.5
Classifier: Programming Language :: Python :: 3.6
Classifier: Programming Language :: Python :: 3.7
Obsoletes: classtools_autocode
Provides-Extra: contracts
Provides-Extra: validate
Provides-Extra: enforce
